<Properties>
  <MonoDevelop.Ide.Workbench ActiveDocument="BoltSigner.cs">
    <Files>
      <File FileName="BoltS3Client.cs" Line="95" Column="14" />
      <File FileName="packages.config" Line="5" Column="16" />
      <File FileName="BoltSigner.cs" Line="56" Column="102" />
    </Files>
    <Pads>
      <Pad Id="ProjectPad">
        <State name="__root__">
          <Node name="ProjectN.Bolt" expanded="True">
            <Node name="ProjectN.Bolt" expanded="True">
              <Node name="BoltSigner.cs" selected="True" />
            </Node>
          </Node>
        </State>
      </Pad>
    </Pads>
  </MonoDevelop.Ide.Workbench>
  <MonoDevelop.Ide.DebuggingService.PinnedWatches />
  <MonoDevelop.Ide.Workspace ActiveConfiguration="Debug" />
  <MonoDevelop.Ide.DebuggingService.Breakpoints>
    <BreakpointStore />
  </MonoDevelop.Ide.DebuggingService.Breakpoints>
  <MultiItemStartupConfigurations />
</Properties>